ipfs_http_client_sdk/__init__.py
ipfs_http_client_sdk/wrap/__init__.py
ipfs_http_client_sdk/wrap/types.py
ipfs_http_client_sdk-0.1.0.dist-info/METADATA
ipfs_http_client_sdk-0.1.0.dist-info/WHEEL
ipfs_http_client_sdk-0.1.0.dist-info/RECORD
