Metadata-Version: 2.1
Name: ipfs-http-client-sdk
Version: 0.1.0
Summary: IPFS HTTP Client for Python
Author: Niraj
Author-email: niraj@polywrap.io
Requires-Python: >=3.10,<4.0
Classifier: Programming Language :: Python :: 3
Classifier: Programming Language :: Python :: 3.10
Classifier: Programming Language :: Python :: 3.11
Requires-Dist: polywrap (>=0.1.0b7,<0.2.0)
